cmem_plugin_number_conversion/__init__.py
cmem_plugin_number_conversion/transform/__init__.py
cmem_plugin_number_conversion-0.7.0.dist-info/METADATA
cmem_plugin_number_conversion-0.7.0.dist-info/WHEEL
cmem_plugin_number_conversion-0.7.0.dist-info/licenses/LICENSE
cmem_plugin_number_conversion-0.7.0.dist-info/RECORD
