Metadata-Version: 2.4
Name: cmem-plugin-number-conversion
Version: 0.7.0
Summary: Convert numbers between binary, octal, decimal and hexadecimal representation.
License: Apache-2.0
License-File: LICENSE
Keywords: eccenca Corporate Memory,plugin,number-conversion
Author: eccenca GmbH
Author-email: cmempy-developer@eccenca.com
Requires-Python: >=3.13,<4.0
Classifier: Development Status :: 4 - Beta
Classifier: Environment :: Plugins
Classifier: License :: OSI Approved :: Apache Software License
Classifier: Programming Language :: Python :: 3
Classifier: Programming Language :: Python :: 3.13
Classifier: Programming Language :: Python :: 3.14
Requires-Dist: cmem-plugin-base (>=4.15.0,<5.0.0)
Project-URL: Homepage, https://github.com/eccenca/cmem-plugin-number-conversion
